LoL/__init__.py
LoL/main.py
LoL.py_Blackcool70-0.0.8.dist-info/LICENSE
LoL.py_Blackcool70-0.0.8.dist-info/METADATA
LoL.py_Blackcool70-0.0.8.dist-info/WHEEL
LoL.py_Blackcool70-0.0.8.dist-info/top_level.txt
LoL.py_Blackcool70-0.0.8.dist-info/RECORD
