Metadata-Version: 2.1
Name: LoL.py-Blackcool70
Version: 0.0.8
Summary: A tiny Riot-league of legends Api wrapper
Home-page: https://github.com/Blackcool70/LoL.py
Author: Blackcool70
Author-email: blackcool70_cool7744@hotmail.com
License: UNKNOWN
Project-URL: Bug Tracker, https://github.com/Blackcool70/LoL.py/issues
Platform: UNKNOWN
Classifier: Programming Language :: Python :: 3
Classifier: License :: OSI Approved :: MIT License
Classifier: Operating System :: OS Independent
Requires-Python: >=3.6
License-File: LICENSE
Requires-Dist: requests
